lmsim/__init__.py
lmsim/metrics.py
lm_sim-0.1.1.dist-info/METADATA
lm_sim-0.1.1.dist-info/WHEEL
lm_sim-0.1.1.dist-info/top_level.txt
lm_sim-0.1.1.dist-info/RECORD
