Metadata-Version: 2.2
Name: lm-sim
Version: 0.1.1
Summary: Python package to compute similarity between LMs
Author-email: Ilze Amanda Auzina <ilze.amanda.auzina@outlook.com>, Shashwat Goel <shashwatnow@gmail.com>, Joschka Strüber <joschka.strueber@bethgelab.org>
License: MIT
Project-URL: Homepage, https://github.com/model-similarity/lm-similarity.git
Project-URL: Projectpage, https://model-similarity.github.io/
Classifier: Programming Language :: Python :: 3
Classifier: Operating System :: OS Independent
Requires-Python: >=3.9
